<?xml version="1.0" encoding="UTF-8"?>
<!DOCTYPE mapper PUBLIC "-//mybatis.org//DTD Mapper 3.0//EN" "http://mybatis.org/dtd/mybatis-3-mapper.dtd">
<mapper namespace="com.rosin.manager.dao.TrackMapper">
  <resultMap id="BaseResultMap" type="com.rosin.manager.model.Track">
    <!--
      WARNING - @mbg.generated
      This element is automatically generated by MyBatis Generator, do not modify.
    -->
    <constructor>
      <idArg column="track_id" javaType="java.lang.Integer" jdbcType="INTEGER" />
      <arg column="task_id" javaType="java.lang.Integer" jdbcType="INTEGER" />
      <arg column="track_type" javaType="java.lang.Integer" jdbcType="INTEGER" />
      <arg column="track_start_time" javaType="java.util.Date" jdbcType="TIMESTAMP" />
      <arg column="track_file" javaType="java.lang.String" jdbcType="VARCHAR" />
      <arg column="trackCreator_id" javaType="java.lang.Integer" jdbcType="INTEGER" />
    </constructor>
  </resultMap>
  <resultMap id="ResultMapWithBLOBs" type="com.rosin.manager.model.Track">
    <!--
      WARNING - @mbg.generated
      This element is automatically generated by MyBatis Generator, do not modify.
    -->
    <constructor>
      <idArg column="track_id" javaType="java.lang.Integer" jdbcType="INTEGER" />
      <arg column="task_id" javaType="java.lang.Integer" jdbcType="INTEGER" />
      <arg column="track_type" javaType="java.lang.Integer" jdbcType="INTEGER" />
      <arg column="track_start_time" javaType="java.util.Date" jdbcType="TIMESTAMP" />
      <arg column="track_file" javaType="java.lang.String" jdbcType="VARCHAR" />
      <arg column="trackCreator_id" javaType="java.lang.Integer" jdbcType="INTEGER" />
      <arg column="track_content" javaType="java.lang.String" jdbcType="LONGVARCHAR" />
    </constructor>
  </resultMap>
  <sql id="Base_Column_List">
    <!--
      WARNING - @mbg.generated
      This element is automatically generated by MyBatis Generator, do not modify.
    -->
    track_id, task_id, track_type, track_start_time, track_file, trackCreator_id
  </sql>
  <sql id="Blob_Column_List">
    <!--
      WARNING - @mbg.generated
      This element is automatically generated by MyBatis Generator, do not modify.
    -->
    track_content
  </sql>
  <select id="selectByPrimaryKey" parameterType="java.lang.Integer" resultMap="ResultMapWithBLOBs">
    <!--
      WARNING - @mbg.generated
      This element is automatically generated by MyBatis Generator, do not modify.
    -->
    select 
    <include refid="Base_Column_List" />
    ,
    <include refid="Blob_Column_List" />
    from track
    where track_id = #{trackId,jdbcType=INTEGER}
  </select>
  <delete id="deleteByPrimaryKey" parameterType="java.lang.Integer">
    <!--
      WARNING - @mbg.generated
      This element is automatically generated by MyBatis Generator, do not modify.
    -->
    delete from track
    where track_id = #{trackId,jdbcType=INTEGER}
  </delete>
  <insert id="insert" parameterType="com.rosin.manager.model.Track">
    <!--
      WARNING - @mbg.generated
      This element is automatically generated by MyBatis Generator, do not modify.
    -->
    insert into track (track_id, task_id, track_type, 
      track_start_time, track_file, trackCreator_id, 
      track_content)
    values (#{trackId,jdbcType=INTEGER}, #{taskId,jdbcType=INTEGER}, #{trackType,jdbcType=INTEGER}, 
      #{trackStartTime,jdbcType=TIMESTAMP}, #{trackFile,jdbcType=VARCHAR}, #{trackcreatorId,jdbcType=INTEGER}, 
      #{trackContent,jdbcType=LONGVARCHAR})
  </insert>
  <insert id="insertSelective" parameterType="com.rosin.manager.model.Track">
    <!--
      WARNING - @mbg.generated
      This element is automatically generated by MyBatis Generator, do not modify.
    -->
    insert into track
    <trim prefix="(" suffix=")" suffixOverrides=",">
      <if test="trackId != null">
        track_id,
      </if>
      <if test="taskId != null">
        task_id,
      </if>
      <if test="trackType != null">
        track_type,
      </if>
      <if test="trackStartTime != null">
        track_start_time,
      </if>
      <if test="trackFile != null">
        track_file,
      </if>
      <if test="trackcreatorId != null">
        trackCreator_id,
      </if>
      <if test="trackContent != null">
        track_content,
      </if>
    </trim>
    <trim prefix="values (" suffix=")" suffixOverrides=",">
      <if test="trackId != null">
        #{trackId,jdbcType=INTEGER},
      </if>
      <if test="taskId != null">
        #{taskId,jdbcType=INTEGER},
      </if>
      <if test="trackType != null">
        #{trackType,jdbcType=INTEGER},
      </if>
      <if test="trackStartTime != null">
        #{trackStartTime,jdbcType=TIMESTAMP},
      </if>
      <if test="trackFile != null">
        #{trackFile,jdbcType=VARCHAR},
      </if>
      <if test="trackcreatorId != null">
        #{trackcreatorId,jdbcType=INTEGER},
      </if>
      <if test="trackContent != null">
        #{trackContent,jdbcType=LONGVARCHAR},
      </if>
    </trim>
  </insert>
  <update id="updateByPrimaryKeySelective" parameterType="com.rosin.manager.model.Track">
    <!--
      WARNING - @mbg.generated
      This element is automatically generated by MyBatis Generator, do not modify.
    -->
    update track
    <set>
      <if test="taskId != null">
        task_id = #{taskId,jdbcType=INTEGER},
      </if>
      <if test="trackType != null">
        track_type = #{trackType,jdbcType=INTEGER},
      </if>
      <if test="trackStartTime != null">
        track_start_time = #{trackStartTime,jdbcType=TIMESTAMP},
      </if>
      <if test="trackFile != null">
        track_file = #{trackFile,jdbcType=VARCHAR},
      </if>
      <if test="trackcreatorId != null">
        trackCreator_id = #{trackcreatorId,jdbcType=INTEGER},
      </if>
      <if test="trackContent != null">
        track_content = #{trackContent,jdbcType=LONGVARCHAR},
      </if>
    </set>
    where track_id = #{trackId,jdbcType=INTEGER}
  </update>
  <update id="updateByPrimaryKeyWithBLOBs" parameterType="com.rosin.manager.model.Track">
    <!--
      WARNING - @mbg.generated
      This element is automatically generated by MyBatis Generator, do not modify.
    -->
    update track
    set task_id = #{taskId,jdbcType=INTEGER},
      track_type = #{trackType,jdbcType=INTEGER},
      track_start_time = #{trackStartTime,jdbcType=TIMESTAMP},
      track_file = #{trackFile,jdbcType=VARCHAR},
      trackCreator_id = #{trackcreatorId,jdbcType=INTEGER},
      track_content = #{trackContent,jdbcType=LONGVARCHAR}
    where track_id = #{trackId,jdbcType=INTEGER}
  </update>
  <update id="updateByPrimaryKey" parameterType="com.rosin.manager.model.Track">
    <!--
      WARNING - @mbg.generated
      This element is automatically generated by MyBatis Generator, do not modify.
    -->
    update track
    set task_id = #{taskId,jdbcType=INTEGER},
      track_type = #{trackType,jdbcType=INTEGER},
      track_start_time = #{trackStartTime,jdbcType=TIMESTAMP},
      track_file = #{trackFile,jdbcType=VARCHAR},
      trackCreator_id = #{trackcreatorId,jdbcType=INTEGER}
    where track_id = #{trackId,jdbcType=INTEGER}
  </update>
</mapper>